[
  {
    "Name": "Cool Plume",
    "Chance": 0.5261192649428571,
    "Url": "https://media3.spiralknights.com/wiki-images/d/d4/Cool_Plume-Equipped.png"
  },
  {
    "Name": "Regal Plume",
    "Chance": 0.5261192649428571,
    "Url": "https://media3.spiralknights.com/wiki-images/c/c1/Regal_Plume-Equipped.png"
  },
  {
    "Name": "Military Plume",
    "Chance": 0.5261192649428571,
    "Url": "https://media3.spiralknights.com/wiki-images/6/6d/Military_Plume-Equipped.png"
  },
  {
    "Name": "Heavy Plume",
    "Chance": 0.5261192649428571,
    "Url": "https://media3.spiralknights.com/wiki-images/0/0e/Heavy_Plume-Equipped.png"
  },
  {
    "Name": "Fancy Plume",
    "Chance": 0.5261192649428571,
    "Url": "https://media3.spiralknights.com/wiki-images/7/7e/Fancy_Plume-Equipped.png"
  },
  {
    "Name": "Dusky Plume",
    "Chance": 0.5261192649428571,
    "Url": "https://media3.spiralknights.com/wiki-images/1/12/Dusky_Plume-Equipped.png"
  },
  {
    "Name": "Toasty Plume",
    "Chance": 0.5261192649428571,
    "Url": "https://media3.spiralknights.com/wiki-images/0/0e/Toasty_Plume-Equipped.png"
  },
  {
    "Name": "Divine Plume",
    "Chance": 0.03688480488,
    "Url": "https://media3.spiralknights.com/wiki-images/b/bb/Divine_Plume-Equipped.png"
  },
  {
    "Name": "Volcanic Plume",
    "Chance": 0.03688480488,
    "Url": "https://media3.spiralknights.com/wiki-images/1/13/Volcanic_Plume-Equipped.png"
  },
  {
    "Name": "**Prismatic Plume**",
    "Chance": 0.00715113564,
    "Url": "https://media3.spiralknights.com/wiki-images/8/89/Prismatic_Plume-Equipped.png"
  },
  {
    "Name": "Cool Ribbon",
    "Chance": 0.5261192649428571,
    "Url": "https://media3.spiralknights.com/wiki-images/e/e6/Cool_Ribbon-Equipped.png"
  },
  {
    "Name": "Regal Ribbon",
    "Chance": 0.5261192649428571,
    "Url": "https://media3.spiralknights.com/wiki-images/8/88/Regal_Ribbon-Equipped.png"
  },
  {
    "Name": "Military Ribbon",
    "Chance": 0.5261192649428571,
    "Url": "https://media3.spiralknights.com/wiki-images/3/3e/Military_Ribbon-Equipped.png"
  },
  {
    "Name": "Heavy Ribbon",
    "Chance": 0.5261192649428571,
    "Url": "https://media3.spiralknights.com/wiki-images/e/e6/Heavy_Ribbon-Equipped.png"
  },
  {
    "Name": "Fancy Ribbon",
    "Chance": 0.5261192649428571,
    "Url": "https://media3.spiralknights.com/wiki-images/f/ff/Fancy_Ribbon-Equipped.png"
  },
  {
    "Name": "Dusky Ribbon",
    "Chance": 0.5261192649428571,
    "Url": "https://media3.spiralknights.com/wiki-images/b/b4/Dusky_Ribbon-Equipped.png"
  },
  {
    "Name": "Toasty Ribbon",
    "Chance": 0.5261192649428571,
    "Url": "https://media3.spiralknights.com/wiki-images/4/48/Toasty_Ribbon-Equipped.png"
  },
  {
    "Name": "Divine Ribbon",
    "Chance": 0.03688480488,
    "Url": "https://media3.spiralknights.com/wiki-images/4/45/Divine_Ribbon-Equipped.png"
  },
  {
    "Name": "Volcanic Ribbon",
    "Chance": 0.03688480488,
    "Url": "https://media3.spiralknights.com/wiki-images/f/f6/Volcanic_Ribbon-Equipped.png"
  },
  {
    "Name": "**Prismatic Ribbon**",
    "Chance": 0.00715113564,
    "Url": "https://media3.spiralknights.com/wiki-images/1/1c/Prismatic_Ribbon-Equipped.png"
  },
  {
    "Name": "Cool Vented Visor",
    "Chance": 0.5261192649428571,
    "Url": "https://media3.spiralknights.com/wiki-images/5/5c/Cool_Vented_Visor-Equipped.png"
  },
  {
    "Name": "Regal Vented Visor",
    "Chance": 0.5261192649428571,
    "Url": "https://media3.spiralknights.com/wiki-images/2/27/Regal_Vented_Visor-Equipped.png"
  },
  {
    "Name": "Military Vented Visor",
    "Chance": 0.5261192649428571,
    "Url": "https://media3.spiralknights.com/wiki-images/a/a4/Military_Vented_Visor-Equipped.png"
  },
  {
    "Name": "Heavy Vented Visor",
    "Chance": 0.5261192649428571,
    "Url": "https://media3.spiralknights.com/wiki-images/9/94/Heavy_Vented_Visor-Equipped.png"
  },
  {
    "Name": "Fancy Vented Visor",
    "Chance": 0.5261192649428571,
    "Url": "https://media3.spiralknights.com/wiki-images/8/84/Fancy_Vented_Visor-Equipped.png"
  },
  {
    "Name": "Dusky Vented Visor",
    "Chance": 0.5261192649428571,
    "Url": "https://media3.spiralknights.com/wiki-images/7/73/Dusky_Vented_Visor-Equipped.png"
  },
  {
    "Name": "Toasty Vented Visor",
    "Chance": 0.5261192649428571,
    "Url": "https://media3.spiralknights.com/wiki-images/e/e1/Toasty_Vented_Visor-Equipped.png"
  },
  {
    "Name": "Divine Vented Visor",
    "Chance": 0.03688480488,
    "Url": "https://media3.spiralknights.com/wiki-images/8/86/Divine_Vented_Visor-Equipped.png"
  },
  {
    "Name": "Volcanic Vented Visor",
    "Chance": 0.03688480488,
    "Url": "https://media3.spiralknights.com/wiki-images/8/89/Volcanic_Vented_Visor-Equipped.png"
  },
  {
    "Name": "**Prismatic Vented Visor**",
    "Chance": 0.00715113564,
    "Url": "https://media3.spiralknights.com/wiki-images/e/ec/Prismatic_Vented_Visor-Equipped.png"
  },
  {
    "Name": "Cool Binocular Visor",
    "Chance": 0.5261192649428571,
    "Url": "https://media3.spiralknights.com/wiki-images/9/92/Cool_Binocular_Visor-Equipped.png"
  },
  {
    "Name": "Regal Binocular Visor",
    "Chance": 0.5261192649428571,
    "Url": "https://media3.spiralknights.com/wiki-images/b/b4/Regal_Binocular_Visor-Equipped.png"
  },
  {
    "Name": "Military Binocular Visor",
    "Chance": 0.5261192649428571,
    "Url": "https://media3.spiralknights.com/wiki-images/f/f2/Military_Binocular_Visor-Equipped.png"
  },
  {
    "Name": "Heavy Binocular Visor",
    "Chance": 0.5261192649428571,
    "Url": "https://media3.spiralknights.com/wiki-images/8/83/Heavy_Binocular_Visor-Equipped.png"
  },
  {
    "Name": "Fancy Binocular Visor",
    "Chance": 0.5261192649428571,
    "Url": "https://media3.spiralknights.com/wiki-images/3/38/Fancy_Binocular_Visor-Equipped.png"
  },
  {
    "Name": "Dusky Binocular Visor",
    "Chance": 0.5261192649428571,
    "Url": "https://media3.spiralknights.com/wiki-images/6/65/Dusky_Binocular_Visor-Equipped.png"
  },
  {
    "Name": "Toasty Binocular Visor",
    "Chance": 0.5261192649428571,
    "Url": "https://media3.spiralknights.com/wiki-images/2/2a/Toasty_Binocular_Visor-Equipped.png"
  },
  {
    "Name": "Divine Binocular Visor",
    "Chance": 0.03688480488,
    "Url": "https://media3.spiralknights.com/wiki-images/4/4c/Divine_Binocular_Visor-Equipped.png"
  },
  {
    "Name": "Volcanic Binocular Visor",
    "Chance": 0.03688480488,
    "Url": "https://media3.spiralknights.com/wiki-images/4/4a/Volcanic_Binocular_Visor-Equipped.png"
  },
  {
    "Name": "**Prismatic Binocular Visor**",
    "Chance": 0.00715113564,
    "Url": "https://media3.spiralknights.com/wiki-images/a/ab/Prismatic_Binocular_Visor-Equipped.png"
  },
  {
    "Name": "Cool Knight Vision Goggles",
    "Chance": 0.5261192649428571,
    "Url": "https://media3.spiralknights.com/wiki-images/3/34/Cool_Knight_Vision_Goggles-Equipped.png"
  },
  {
    "Name": "Regal Knight Vision Goggles",
    "Chance": 0.5261192649428571,
    "Url": "https://media3.spiralknights.com/wiki-images/2/23/Regal_Knight_Vision_Goggles-Equipped.png"
  },
  {
    "Name": "Military Knight Vision Goggles",
    "Chance": 0.5261192649428571,
    "Url": "https://media3.spiralknights.com/wiki-images/8/83/Military_Knight_Vision_Goggles-Equipped.png"
  },
  {
    "Name": "Heavy Knight Vision Goggles",
    "Chance": 0.5261192649428571,
    "Url": "https://media3.spiralknights.com/wiki-images/2/2a/Heavy_Knight_Vision_Goggles-Equipped.png"
  },
  {
    "Name": "Fancy Knight Vision Goggles",
    "Chance": 0.5261192649428571,
    "Url": "https://media3.spiralknights.com/wiki-images/d/d3/Fancy_Knight_Vision_Goggles-Equipped.png"
  },
  {
    "Name": "Dusky Knight Vision Goggles",
    "Chance": 0.5261192649428571,
    "Url": "https://media3.spiralknights.com/wiki-images/1/14/Dusky_Knight_Vision_Goggles-Equipped.png"
  },
  {
    "Name": "Toasty Knight Vision Goggles",
    "Chance": 0.5261192649428571,
    "Url": "https://media3.spiralknights.com/wiki-images/c/ce/Toasty_Knight_Vision_Goggles-Equipped.png"
  },
  {
    "Name": "Divine Knight Vision Goggles",
    "Chance": 0.03688480488,
    "Url": "https://media3.spiralknights.com/wiki-images/4/4e/Divine_Knight_Vision_Goggles-Equipped.png"
  },
  {
    "Name": "Volcanic Knight Vision Goggles",
    "Chance": 0.03688480488,
    "Url": "https://media3.spiralknights.com/wiki-images/8/84/Volcanic_Knight_Vision_Goggles-Equipped.png"
  },
  {
    "Name": "**Prismatic Knight Vision Goggles**",
    "Chance": 0.00715113564,
    "Url": "https://media3.spiralknights.com/wiki-images/f/f3/Prismatic_Knight_Vision_Goggles-Equipped.png"
  },
  {
    "Name": "Cool Game Face",
    "Chance": 0.5261192649428571,
    "Url": "https://media3.spiralknights.com/wiki-images/7/77/Cool_Game_Face-Equipped.png"
  },
  {
    "Name": "Regal Game Face",
    "Chance": 0.5261192649428571,
    "Url": "https://media3.spiralknights.com/wiki-images/6/63/Regal_Game_Face-Equipped.png"
  },
  {
    "Name": "Military Game Face",
    "Chance": 0.5261192649428571,
    "Url": "https://media3.spiralknights.com/wiki-images/a/a1/Military_Game_Face-Equipped.png"
  },
  {
    "Name": "Heavy Game Face",
    "Chance": 0.5261192649428571,
    "Url": "https://media3.spiralknights.com/wiki-images/f/f4/Heavy_Game_Face-Equipped.png"
  },
  {
    "Name": "Fancy Game Face",
    "Chance": 0.5261192649428571,
    "Url": "https://media3.spiralknights.com/wiki-images/8/87/Fancy_Game_Face-Equipped.png"
  },
  {
    "Name": "Dusky Game Face",
    "Chance": 0.5261192649428571,
    "Url": "https://media3.spiralknights.com/wiki-images/7/73/Dusky_Game_Face-Equipped.png"
  },
  {
    "Name": "Toasty Game Face",
    "Chance": 0.5261192649428571,
    "Url": "https://media3.spiralknights.com/wiki-images/2/26/Toasty_Game_Face-Equipped.png"
  },
  {
    "Name": "Divine Game Face",
    "Chance": 0.03688480488,
    "Url": "https://media3.spiralknights.com/wiki-images/6/6f/Divine_Game_Face-Equipped.png"
  },
  {
    "Name": "Volcanic Game Face",
    "Chance": 0.03688480488,
    "Url": "https://media3.spiralknights.com/wiki-images/4/40/Volcanic_Game_Face-Equipped.png"
  },
  {
    "Name": "**Prismatic Game Face**",
    "Chance": 0.00715113564,
    "Url": "https://media3.spiralknights.com/wiki-images/a/ad/Prismatic_Game_Face-Equipped.png"
  },
  {
    "Name": "Cool Helm-Mounted Display",
    "Chance": 0.5261192649428571,
    "Url": "https://media3.spiralknights.com/wiki-images/1/15/Cool_Helm-Mounted_Display-Equipped.png"
  },
  {
    "Name": "Regal Helm-Mounted Display",
    "Chance": 0.5261192649428571,
    "Url": "https://media3.spiralknights.com/wiki-images/9/9a/Regal_Helm-Mounted_Display-Equipped.png"
  },
  {
    "Name": "Military Helm-Mounted Display",
    "Chance": 0.5261192649428571,
    "Url": "https://media3.spiralknights.com/wiki-images/f/f7/Military_Helm-Mounted_Display-Equipped.png"
  },
  {
    "Name": "Heavy Helm-Mounted Display",
    "Chance": 0.5261192649428571,
    "Url": "https://media3.spiralknights.com/wiki-images/7/7e/Heavy_Helm-Mounted_Display-Equipped.png"
  },
  {
    "Name": "Fancy Helm-Mounted Display",
    "Chance": 0.5261192649428571,
    "Url": "https://media3.spiralknights.com/wiki-images/6/64/Fancy_Helm-Mounted_Display-Equipped.png"
  },
  {
    "Name": "Dusky Helm-Mounted Display",
    "Chance": 0.5261192649428571,
    "Url": "https://media3.spiralknights.com/wiki-images/0/0e/Dusky_Helm-Mounted_Display-Equipped.png"
  },
  {
    "Name": "Toasty Helm-Mounted Display",
    "Chance": 0.5261192649428571,
    "Url": "https://media3.spiralknights.com/wiki-images/7/7d/Toasty_Helm-Mounted_Display-Equipped.png"
  },
  {
    "Name": "Divine Helm-Mounted Display",
    "Chance": 0.03688480488,
    "Url": "https://media3.spiralknights.com/wiki-images/c/c8/Divine_Helm-Mounted_Display-Equipped.png"
  },
  {
    "Name": "Volcanic Helm-Mounted Display",
    "Chance": 0.03688480488,
    "Url": "https://media3.spiralknights.com/wiki-images/2/2c/Volcanic_Helm-Mounted_Display-Equipped.png"
  },
  {
    "Name": "**Prismatic Helm-Mounted Display**",
    "Chance": 0.00715113564,
    "Url": "https://media3.spiralknights.com/wiki-images/5/58/Prismatic_Helm-Mounted_Display-Equipped.png"
  },
  {
    "Name": "Cool Goggles",
    "Chance": 0.5261192649428571,
    "Url": "https://media3.spiralknights.com/wiki-images/5/57/Cool_Goggles-Equipped.png"
  },
  {
    "Name": "Regal Goggles",
    "Chance": 0.5261192649428571,
    "Url": "https://media3.spiralknights.com/wiki-images/e/ec/Regal_Goggles-Equipped.png"
  },
  {
    "Name": "Military Goggles",
    "Chance": 0.5261192649428571,
    "Url": "https://media3.spiralknights.com/wiki-images/6/6f/Military_Goggles-Equipped.png"
  },
  {
    "Name": "Heavy Goggles",
    "Chance": 0.5261192649428571,
    "Url": "https://media3.spiralknights.com/wiki-images/6/6b/Heavy_Goggles-Equipped.png"
  },
  {
    "Name": "Fancy Goggles",
    "Chance": 0.5261192649428571,
    "Url": "https://media3.spiralknights.com/wiki-images/6/67/Fancy_Goggles-Equipped.png"
  },
  {
    "Name": "Dusky Goggles",
    "Chance": 0.5261192649428571,
    "Url": "https://media3.spiralknights.com/wiki-images/3/3b/Dusky_Goggles-Equipped.png"
  },
  {
    "Name": "Toasty Goggles",
    "Chance": 0.5261192649428571,
    "Url": "https://media3.spiralknights.com/wiki-images/e/e1/Toasty_Goggles-Equipped.png"
  },
  {
    "Name": "Divine Goggles",
    "Chance": 0.03688480488,
    "Url": "https://media3.spiralknights.com/wiki-images/3/3f/Divine_Goggles-Equipped.png"
  },
  {
    "Name": "Volcanic Goggles",
    "Chance": 0.03688480488,
    "Url": "https://media3.spiralknights.com/wiki-images/3/30/Volcanic_Goggles-Equipped.png"
  },
  {
    "Name": "**Prismatic Goggles**",
    "Chance": 0.00715113564,
    "Url": "https://media3.spiralknights.com/wiki-images/8/84/Prismatic_Goggles-Equipped.png"
  },
  {
    "Name": "Cool Com Unit",
    "Chance": 0.5261192649428571,
    "Url": "https://media3.spiralknights.com/wiki-images/7/72/Cool_Com_Unit-Equipped.png"
  },
  {
    "Name": "Regal Com Unit",
    "Chance": 0.5261192649428571,
    "Url": "https://media3.spiralknights.com/wiki-images/5/5e/Regal_Com_Unit-Equipped.png"
  },
  {
    "Name": "Military Com Unit",
    "Chance": 0.5261192649428571,
    "Url": "https://media3.spiralknights.com/wiki-images/d/de/Military_Com_Unit-Equipped.png"
  },
  {
    "Name": "Heavy Com Unit",
    "Chance": 0.5261192649428571,
    "Url": "https://media3.spiralknights.com/wiki-images/f/fa/Heavy_Com_Unit-Equipped.png"
  },
  {
    "Name": "Fancy Com Unit",
    "Chance": 0.5261192649428571,
    "Url": "https://media3.spiralknights.com/wiki-images/2/28/Fancy_Com_Unit-Equipped.png"
  },
  {
    "Name": "Dusky Com Unit",
    "Chance": 0.5261192649428571,
    "Url": "https://media3.spiralknights.com/wiki-images/a/a2/Dusky_Com_Unit-Equipped.png"
  },
  {
    "Name": "Toasty Com Unit",
    "Chance": 0.5261192649428571,
    "Url": "https://media3.spiralknights.com/wiki-images/e/ee/Toasty_Com_Unit-Equipped.png"
  },
  {
    "Name": "Divine Com Unit",
    "Chance": 0.03688480488,
    "Url": "https://media3.spiralknights.com/wiki-images/8/8c/Divine_Com_Unit-Equipped.png"
  },
  {
    "Name": "Volcanic Com Unit",
    "Chance": 0.03688480488,
    "Url": "https://media3.spiralknights.com/wiki-images/0/03/Volcanic_Com_Unit-Equipped.png"
  },
  {
    "Name": "**Prismatic Com Unit**",
    "Chance": 0.00715113564,
    "Url": "https://media3.spiralknights.com/wiki-images/5/54/Prismatic_Com_Unit-Equipped.png"
  },
  {
    "Name": "Cool Mecha Wings",
    "Chance": 0.5261192649428571,
    "Url": "https://media3.spiralknights.com/wiki-images/3/3d/Cool_Mecha_Wings-Equipped.png"
  },
  {
    "Name": "Regal Mecha Wings",
    "Chance": 0.5261192649428571,
    "Url": "https://media3.spiralknights.com/wiki-images/7/76/Regal_Mecha_Wings-Equipped.png"
  },
  {
    "Name": "Military Mecha Wings",
    "Chance": 0.5261192649428571,
    "Url": "https://media3.spiralknights.com/wiki-images/0/0a/Military_Mecha_Wings-Equipped.png"
  },
  {
    "Name": "Heavy Mecha Wings",
    "Chance": 0.5261192649428571,
    "Url": "https://media3.spiralknights.com/wiki-images/7/70/Heavy_Mecha_Wings-Equipped.png"
  },
  {
    "Name": "Fancy Mecha Wings",
    "Chance": 0.5261192649428571,
    "Url": "https://media3.spiralknights.com/wiki-images/e/e1/Fancy_Mecha_Wings-Equipped.png"
  },
  {
    "Name": "Dusky Mecha Wings",
    "Chance": 0.5261192649428571,
    "Url": "https://media3.spiralknights.com/wiki-images/3/3e/Dusky_Mecha_Wings-Equipped.png"
  },
  {
    "Name": "Toasty Mecha Wings",
    "Chance": 0.5261192649428571,
    "Url": "https://media3.spiralknights.com/wiki-images/f/ff/Toasty_Mecha_Wings-Equipped.png"
  },
  {
    "Name": "Divine Mecha Wings",
    "Chance": 0.03688480488,
    "Url": "https://media3.spiralknights.com/wiki-images/5/50/Divine_Mecha_Wings-Equipped.png"
  },
  {
    "Name": "Volcanic Mecha Wings",
    "Chance": 0.03688480488,
    "Url": "https://media3.spiralknights.com/wiki-images/1/13/Volcanic_Mecha_Wings-Equipped.png"
  },
  {
    "Name": "**Prismatic Mecha Wings**",
    "Chance": 0.00715113564,
    "Url": "https://media3.spiralknights.com/wiki-images/f/fa/Prismatic_Mecha_Wings-Equipped.png"
  },
  {
    "Name": "Cool Helm Guards",
    "Chance": 0.5261192649428571,
    "Url": "https://media3.spiralknights.com/wiki-images/4/46/Cool_Helm_Guards-Equipped.png"
  },
  {
    "Name": "Regal Helm Guards",
    "Chance": 0.5261192649428571,
    "Url": "https://media3.spiralknights.com/wiki-images/f/fb/Regal_Helm_Guards-Equipped.png"
  },
  {
    "Name": "Military Helm Guards",
    "Chance": 0.5261192649428571,
    "Url": "https://media3.spiralknights.com/wiki-images/6/62/Military_Helm_Guards-Equipped.png"
  },
  {
    "Name": "Heavy Helm Guards",
    "Chance": 0.5261192649428571,
    "Url": "https://media3.spiralknights.com/wiki-images/7/73/Heavy_Helm_Guards-Equipped.png"
  },
  {
    "Name": "Fancy Helm Guards",
    "Chance": 0.5261192649428571,
    "Url": "https://media3.spiralknights.com/wiki-images/8/84/Fancy_Helm_Guards-Equipped.png"
  },
  {
    "Name": "Dusky Helm Guards",
    "Chance": 0.5261192649428571,
    "Url": "https://media3.spiralknights.com/wiki-images/3/34/Dusky_Helm_Guards-Equipped.png"
  },
  {
    "Name": "Toasty Helm Guards",
    "Chance": 0.5261192649428571,
    "Url": "https://media3.spiralknights.com/wiki-images/5/55/Toasty_Helm_Guards-Equipped.png"
  },
  {
    "Name": "Divine Helm Guards",
    "Chance": 0.03688480488,
    "Url": "https://media3.spiralknights.com/wiki-images/2/24/Divine_Helm_Guards-Equipped.png"
  },
  {
    "Name": "Volcanic Helm Guards",
    "Chance": 0.03688480488,
    "Url": "https://media3.spiralknights.com/wiki-images/3/3b/Volcanic_Helm_Guards-Equipped.png"
  },
  {
    "Name": "**Prismatic Helm Guards**",
    "Chance": 0.00715113564,
    "Url": "https://media3.spiralknights.com/wiki-images/0/0c/Prismatic_Helm_Guards-Equipped.png"
  },
  {
    "Name": "Cool Bolted Vee",
    "Chance": 0.5261192649428571,
    "Url": "https://media3.spiralknights.com/wiki-images/9/9e/Cool_Bolted_Vee-Equipped.png"
  },
  {
    "Name": "Regal Bolted Vee",
    "Chance": 0.5261192649428571,
    "Url": "https://media3.spiralknights.com/wiki-images/d/d8/Regal_Bolted_Vee-Equipped.png"
  },
  {
    "Name": "Military Bolted Vee",
    "Chance": 0.5261192649428571,
    "Url": "https://media3.spiralknights.com/wiki-images/6/60/Military_Bolted_Vee-Equipped.png"
  },
  {
    "Name": "Heavy Bolted Vee",
    "Chance": 0.5261192649428571,
    "Url": "https://media3.spiralknights.com/wiki-images/c/c4/Heavy_Bolted_Vee-Equipped.png"
  },
  {
    "Name": "Fancy Bolted Vee",
    "Chance": 0.5261192649428571,
    "Url": "https://media3.spiralknights.com/wiki-images/9/93/Fancy_Bolted_Vee-Equipped.png"
  },
  {
    "Name": "Dusky Bolted Vee",
    "Chance": 0.5261192649428571,
    "Url": "https://media3.spiralknights.com/wiki-images/4/49/Dusky_Bolted_Vee-Equipped.png"
  },
  {
    "Name": "Toasty Bolted Vee",
    "Chance": 0.5261192649428571,
    "Url": "https://media3.spiralknights.com/wiki-images/7/7b/Toasty_Bolted_Vee-Equipped.png"
  },
  {
    "Name": "Divine Bolted Vee",
    "Chance": 0.03688480488,
    "Url": "https://media3.spiralknights.com/wiki-images/d/d3/Divine_Bolted_Vee-Equipped.png"
  },
  {
    "Name": "Volcanic Bolted Vee",
    "Chance": 0.03688480488,
    "Url": "https://media3.spiralknights.com/wiki-images/f/f9/Volcanic_Bolted_Vee-Equipped.png"
  },
  {
    "Name": "**Prismatic Bolted Vee**",
    "Chance": 0.00715113564,
    "Url": "https://media3.spiralknights.com/wiki-images/f/f5/Prismatic_Bolted_Vee-Equipped.png"
  },
  {
    "Name": "Cool Headband",
    "Chance": 0.5261192649428571,
    "Url": "https://media3.spiralknights.com/wiki-images/0/02/Cool_Headband-Equipped.png"
  },
  {
    "Name": "Regal Headband",
    "Chance": 0.5261192649428571,
    "Url": "https://media3.spiralknights.com/wiki-images/b/b6/Regal_Headband-Equipped.png"
  },
  {
    "Name": "Military Headband",
    "Chance": 0.5261192649428571,
    "Url": "https://media3.spiralknights.com/wiki-images/0/0a/Military_Headband-Equipped.png"
  },
  {
    "Name": "Heavy Headband",
    "Chance": 0.5261192649428571,
    "Url": "https://media3.spiralknights.com/wiki-images/d/da/Heavy_Headband-Equipped.png"
  },
  {
    "Name": "Fancy Headband",
    "Chance": 0.5261192649428571,
    "Url": "https://media3.spiralknights.com/wiki-images/8/85/Fancy_Headband-Equipped.png"
  },
  {
    "Name": "Dusky Headband",
    "Chance": 0.5261192649428571,
    "Url": "https://media3.spiralknights.com/wiki-images/2/26/Dusky_Headband-Equipped.png"
  },
  {
    "Name": "Toasty Headband",
    "Chance": 0.5261192649428571,
    "Url": "https://media3.spiralknights.com/wiki-images/a/a6/Toasty_Headband-Equipped.png"
  },
  {
    "Name": "Divine Headband",
    "Chance": 0.03688480488,
    "Url": "https://media3.spiralknights.com/wiki-images/3/31/Divine_Headband-Equipped.png"
  },
  {
    "Name": "Volcanic Headband",
    "Chance": 0.03688480488,
    "Url": "https://media3.spiralknights.com/wiki-images/d/d7/Volcanic_Headband-Equipped.png"
  },
  {
    "Name": "**Prismatic Headband**",
    "Chance": 0.00715113564,
    "Url": "https://media3.spiralknights.com/wiki-images/6/67/Prismatic_Headband-Equipped.png"
  },
  {
    "Name": "Cool Wide Vee",
    "Chance": 0.5261192649428571,
    "Url": "https://media3.spiralknights.com/wiki-images/9/9d/Cool_Wide_Vee-Equipped.png"
  },
  {
    "Name": "Regal Wide Vee",
    "Chance": 0.5261192649428571,
    "Url": "https://media3.spiralknights.com/wiki-images/1/1b/Regal_Wide_Vee-Equipped.png"
  },
  {
    "Name": "Military Wide Vee",
    "Chance": 0.5261192649428571,
    "Url": "https://media3.spiralknights.com/wiki-images/4/4d/Military_Wide_Vee-Equipped.png"
  },
  {
    "Name": "Heavy Wide Vee",
    "Chance": 0.5261192649428571,
    "Url": "https://media3.spiralknights.com/wiki-images/3/3c/Heavy_Wide_Vee-Equipped.png"
  },
  {
    "Name": "Fancy Wide Vee",
    "Chance": 0.5261192649428571,
    "Url": "https://media3.spiralknights.com/wiki-images/7/71/Fancy_Wide_Vee-Equipped.png"
  },
  {
    "Name": "Dusky Wide Vee",
    "Chance": 0.5261192649428571,
    "Url": "https://media3.spiralknights.com/wiki-images/8/8c/Dusky_Wide_Vee-Equipped.png"
  },
  {
    "Name": "Toasty Wide Vee",
    "Chance": 0.5261192649428571,
    "Url": "https://media3.spiralknights.com/wiki-images/3/38/Toasty_Wide_Vee-Equipped.png"
  },
  {
    "Name": "Divine Wide Vee",
    "Chance": 0.03688480488,
    "Url": "https://media3.spiralknights.com/wiki-images/b/b0/Divine_Wide_Vee-Equipped.png"
  },
  {
    "Name": "Volcanic Wide Vee",
    "Chance": 0.03688480488,
    "Url": "https://media3.spiralknights.com/wiki-images/e/eb/Volcanic_Wide_Vee-Equipped.png"
  },
  {
    "Name": "**Prismatic Wide Vee**",
    "Chance": 0.00715113564,
    "Url": "https://media3.spiralknights.com/wiki-images/f/f1/Prismatic_Wide_Vee-Equipped.png"
  },
  {
    "Name": "Cool Maid Headband",
    "Chance": 0.5261192649428571,
    "Url": "https://media3.spiralknights.com/wiki-images/f/f9/Cool_Maid_Headband-Equipped.png"
  },
  {
    "Name": "Regal Maid Headband",
    "Chance": 0.5261192649428571,
    "Url": "https://media3.spiralknights.com/wiki-images/9/95/Regal_Maid_Headband-Equipped.png"
  },
  {
    "Name": "Military Maid Headband",
    "Chance": 0.5261192649428571,
    "Url": "https://media3.spiralknights.com/wiki-images/1/1b/Military_Maid_Headband-Equipped.png"
  },
  {
    "Name": "Heavy Maid Headband",
    "Chance": 0.5261192649428571,
    "Url": "https://media3.spiralknights.com/wiki-images/d/d2/Heavy_Maid_Headband-Equipped.png"
  },
  {
    "Name": "Fancy Maid Headband",
    "Chance": 0.5261192649428571,
    "Url": "https://media3.spiralknights.com/wiki-images/0/04/Fancy_Maid_Headband-Equipped.png"
  },
  {
    "Name": "Dusky Maid Headband",
    "Chance": 0.5261192649428571,
    "Url": "https://media3.spiralknights.com/wiki-images/2/26/Dusky_Maid_Headband-Equipped.png"
  },
  {
    "Name": "Toasty Maid Headband",
    "Chance": 0.5261192649428571,
    "Url": "https://media3.spiralknights.com/wiki-images/0/0f/Toasty_Maid_Headband-Equipped.png"
  },
  {
    "Name": "Divine Maid Headband",
    "Chance": 0.03688480488,
    "Url": "https://media3.spiralknights.com/wiki-images/c/c9/Divine_Maid_Headband-Equipped.png"
  },
  {
    "Name": "Volcanic Maid Headband",
    "Chance": 0.03688480488,
    "Url": "https://media3.spiralknights.com/wiki-images/8/87/Volcanic_Maid_Headband-Equipped.png"
  },
  {
    "Name": "**Prismatic Maid Headband**",
    "Chance": 0.00715113564,
    "Url": "https://media3.spiralknights.com/wiki-images/a/aa/Prismatic_Maid_Headband-Equipped.png"
  },
  {
    "Name": "Cool Flower",
    "Chance": 0.5261192649428571,
    "Url": "https://media3.spiralknights.com/wiki-images/6/6f/Cool_Flower-Equipped.png"
  },
  {
    "Name": "Regal Flower",
    "Chance": 0.5261192649428571,
    "Url": "https://media3.spiralknights.com/wiki-images/6/6a/Regal_Flower-Equipped.png"
  },
  {
    "Name": "Military Flower",
    "Chance": 0.5261192649428571,
    "Url": "https://media3.spiralknights.com/wiki-images/1/1c/Military_Flower-Equipped.png"
  },
  {
    "Name": "Heavy Flower",
    "Chance": 0.5261192649428571,
    "Url": "https://media3.spiralknights.com/wiki-images/d/d3/Heavy_Flower-Equipped.png"
  },
  {
    "Name": "Fancy Flower",
    "Chance": 0.5261192649428571,
    "Url": "https://media3.spiralknights.com/wiki-images/5/5b/Fancy_Flower-Equipped.png"
  },
  {
    "Name": "Dusky Flower",
    "Chance": 0.5261192649428571,
    "Url": "https://media3.spiralknights.com/wiki-images/3/31/Dusky_Flower-Equipped.png"
  },
  {
    "Name": "Toasty Flower",
    "Chance": 0.5261192649428571,
    "Url": "https://media3.spiralknights.com/wiki-images/0/0a/Toasty_Flower-Equipped.png"
  },
  {
    "Name": "Divine Flower",
    "Chance": 0.03688480488,
    "Url": "https://media3.spiralknights.com/wiki-images/6/6e/Divine_Flower-Equipped.png"
  },
  {
    "Name": "Volcanic Flower",
    "Chance": 0.03688480488,
    "Url": "https://media3.spiralknights.com/wiki-images/c/c8/Volcanic_Flower-Equipped.png"
  },
  {
    "Name": "**Prismatic Flower**",
    "Chance": 0.00715113564,
    "Url": "https://media3.spiralknights.com/wiki-images/7/7c/Prismatic_Flower-Equipped.png"
  },
  {
    "Name": "Cool Long Feather",
    "Chance": 0.4207857752228571,
    "Url": "https://media3.spiralknights.com/wiki-images/4/48/Cool_Long_Feather-Equipped.png"
  },
  {
    "Name": "Regal Long Feather",
    "Chance": 0.4207857752228571,
    "Url": "https://media3.spiralknights.com/wiki-images/4/48/Regal_Long_Feather-Equipped.png"
  },
  {
    "Name": "Military Long Feather",
    "Chance": 0.4207857752228571,
    "Url": "https://media3.spiralknights.com/wiki-images/5/56/Military_Long_Feather-Equipped.png"
  },
  {
    "Name": "Heavy Long Feather",
    "Chance": 0.4207857752228571,
    "Url": "https://media3.spiralknights.com/wiki-images/5/56/Heavy_Long_Feather-Equipped.png"
  },
  {
    "Name": "Fancy Long Feather",
    "Chance": 0.4207857752228571,
    "Url": "https://media3.spiralknights.com/wiki-images/d/de/Fancy_Long_Feather-Equipped.png"
  },
  {
    "Name": "Dusky Long Feather",
    "Chance": 0.4207857752228571,
    "Url": "https://media3.spiralknights.com/wiki-images/2/29/Dusky_Long_Feather-Equipped.png"
  },
  {
    "Name": "Toasty Long Feather",
    "Chance": 0.4207857752228571,
    "Url": "https://media3.spiralknights.com/wiki-images/4/44/Toasty_Long_Feather-Equipped.png"
  },
  {
    "Name": "Divine Long Feather",
    "Chance": 0.029500157568,
    "Url": "https://media3.spiralknights.com/wiki-images/3/31/Divine_Long_Feather-Equipped.png"
  },
  {
    "Name": "Volcanic Long Feather",
    "Chance": 0.029500157568,
    "Url": "https://media3.spiralknights.com/wiki-images/4/4e/Volcanic_Long_Feather-Equipped.png"
  },
  {
    "Name": "**Prismatic Long Feather**",
    "Chance": 0.005719418304,
    "Url": "https://media3.spiralknights.com/wiki-images/a/a8/Prismatic_Long_Feather-Equipped.png"
  },
  {
    "Name": "Cool Vertical Vents",
    "Chance": 0.4207857752228571,
    "Url": "https://media3.spiralknights.com/wiki-images/0/0c/Cool_Vertical_Vents-Equipped.png"
  },
  {
    "Name": "Regal Vertical Vents",
    "Chance": 0.4207857752228571,
    "Url": "https://media3.spiralknights.com/wiki-images/a/af/Regal_Vertical_Vents-Equipped.png"
  },
  {
    "Name": "Military Vertical Vents",
    "Chance": 0.4207857752228571,
    "Url": "https://media3.spiralknights.com/wiki-images/e/ef/Military_Vertical_Vents-Equipped.png"
  },
  {
    "Name": "Heavy Vertical Vents",
    "Chance": 0.4207857752228571,
    "Url": "https://media3.spiralknights.com/wiki-images/3/3a/Heavy_Vertical_Vents-Equipped.png"
  },
  {
    "Name": "Fancy Vertical Vents",
    "Chance": 0.4207857752228571,
    "Url": "https://media3.spiralknights.com/wiki-images/4/4a/Fancy_Vertical_Vents-Equipped.png"
  },
  {
    "Name": "Dusky Vertical Vents",
    "Chance": 0.4207857752228571,
    "Url": "https://media3.spiralknights.com/wiki-images/2/2a/Dusky_Vertical_Vents-Equipped.png"
  },
  {
    "Name": "Toasty Vertical Vents",
    "Chance": 0.4207857752228571,
    "Url": "https://media3.spiralknights.com/wiki-images/f/f2/Toasty_Vertical_Vents-Equipped.png"
  },
  {
    "Name": "Divine Vertical Vents",
    "Chance": 0.029500157568,
    "Url": "https://media3.spiralknights.com/wiki-images/2/29/Divine_Vertical_Vents-Equipped.png"
  },
  {
    "Name": "Volcanic Vertical Vents",
    "Chance": 0.029500157568,
    "Url": "https://media3.spiralknights.com/wiki-images/f/f1/Volcanic_Vertical_Vents-Equipped.png"
  },
  {
    "Name": "**Prismatic Vertical Vents**",
    "Chance": 0.005719418304,
    "Url": "https://media3.spiralknights.com/wiki-images/3/33/Prismatic_Vertical_Vents-Equipped.png"
  },
  {
    "Name": "Cool Pipe",
    "Chance": 0.4207857752228571,
    "Url": "https://media3.spiralknights.com/wiki-images/3/3b/Cool_Pipe-Equipped.png"
  },
  {
    "Name": "Regal Pipe",
    "Chance": 0.4207857752228571,
    "Url": "https://media3.spiralknights.com/wiki-images/1/18/Regal_Pipe-Equipped.png"
  },
  {
    "Name": "Military Pipe",
    "Chance": 0.4207857752228571,
    "Url": "https://media3.spiralknights.com/wiki-images/8/85/Military_Pipe-Equipped.png"
  },
  {
    "Name": "Heavy Pipe",
    "Chance": 0.4207857752228571,
    "Url": "https://media3.spiralknights.com/wiki-images/d/db/Heavy_Pipe-Equipped.png"
  },
  {
    "Name": "Fancy Pipe",
    "Chance": 0.4207857752228571,
    "Url": "https://media3.spiralknights.com/wiki-images/c/cd/Fancy_Pipe-Equipped.png"
  },
  {
    "Name": "Dusky Pipe",
    "Chance": 0.4207857752228571,
    "Url": "https://media3.spiralknights.com/wiki-images/c/c3/Dusky_Pipe-Equipped.png"
  },
  {
    "Name": "Toasty Pipe",
    "Chance": 0.4207857752228571,
    "Url": "https://media3.spiralknights.com/wiki-images/2/20/Toasty_Pipe-Equipped.png"
  },
  {
    "Name": "Divine Pipe",
    "Chance": 0.029500157568,
    "Url": "https://media3.spiralknights.com/wiki-images/0/03/Divine_Pipe-Equipped.png"
  },
  {
    "Name": "Volcanic Pipe",
    "Chance": 0.029500157568,
    "Url": "https://media3.spiralknights.com/wiki-images/8/8b/Volcanic_Pipe-Equipped.png"
  },
  {
    "Name": "**Prismatic Pipe**",
    "Chance": 0.005719418304,
    "Url": "https://media3.spiralknights.com/wiki-images/f/f3/Prismatic_Pipe-Equipped.png"
  },
  {
    "Name": "Cool Glasses",
    "Chance": 0.4207857752228571,
    "Url": "https://media3.spiralknights.com/wiki-images/1/15/Cool_Glasses-Equipped.png"
  },
  {
    "Name": "Regal Glasses",
    "Chance": 0.4207857752228571,
    "Url": "https://media3.spiralknights.com/wiki-images/4/4f/Regal_Glasses-Equipped.png"
  },
  {
    "Name": "Military Glasses",
    "Chance": 0.4207857752228571,
    "Url": "https://media3.spiralknights.com/wiki-images/9/92/Military_Glasses-Equipped.png"
  },
  {
    "Name": "Heavy Glasses",
    "Chance": 0.4207857752228571,
    "Url": "https://media3.spiralknights.com/wiki-images/d/db/Heavy_Glasses-Equipped.png"
  },
  {
    "Name": "Fancy Glasses",
    "Chance": 0.4207857752228571,
    "Url": "https://media3.spiralknights.com/wiki-images/8/80/Fancy_Glasses-Equipped.png"
  },
  {
    "Name": "Dusky Glasses",
    "Chance": 0.4207857752228571,
    "Url": "https://media3.spiralknights.com/wiki-images/b/b2/Dusky_Glasses-Equipped.png"
  },
  {
    "Name": "Toasty Glasses",
    "Chance": 0.4207857752228571,
    "Url": "https://media3.spiralknights.com/wiki-images/b/b6/Toasty_Glasses-Equipped.png"
  },
  {
    "Name": "Divine Glasses",
    "Chance": 0.029500157568,
    "Url": "https://media3.spiralknights.com/wiki-images/e/ef/Divine_Glasses-Equipped.png"
  },
  {
    "Name": "Volcanic Glasses",
    "Chance": 0.029500157568,
    "Url": "https://media3.spiralknights.com/wiki-images/2/2a/Volcanic_Glasses-Equipped.png"
  },
  {
    "Name": "**Prismatic Glasses**",
    "Chance": 0.005719418304,
    "Url": "https://media3.spiralknights.com/wiki-images/d/d1/Prismatic_Glasses-Equipped.png"
  },
  {
    "Name": "Cool Maedate",
    "Chance": 0.4207857752228571,
    "Url": "https://media3.spiralknights.com/wiki-images/1/15/Cool_Maedate-Equipped.png"
  },
  {
    "Name": "Regal Maedate",
    "Chance": 0.4207857752228571,
    "Url": "https://media3.spiralknights.com/wiki-images/3/37/Regal_Maedate-Equipped.png"
  },
  {
    "Name": "Military Maedate",
    "Chance": 0.4207857752228571,
    "Url": "https://media3.spiralknights.com/wiki-images/e/ee/Military_Maedate-Equipped.png"
  },
  {
    "Name": "Heavy Maedate",
    "Chance": 0.4207857752228571,
    "Url": "https://media3.spiralknights.com/wiki-images/9/90/Heavy_Maedate-Equipped.png"
  },
  {
    "Name": "Fancy Maedate",
    "Chance": 0.4207857752228571,
    "Url": "https://media3.spiralknights.com/wiki-images/d/dc/Fancy_Maedate-Equipped.png"
  },
  {
    "Name": "Dusky Maedate",
    "Chance": 0.4207857752228571,
    "Url": "https://media3.spiralknights.com/wiki-images/e/e0/Dusky_Maedate-Equipped.png"
  },
  {
    "Name": "Toasty Maedate",
    "Chance": 0.4207857752228571,
    "Url": "https://media3.spiralknights.com/wiki-images/0/03/Toasty_Maedate-Equipped.png"
  },
  {
    "Name": "Divine Maedate",
    "Chance": 0.029500157568,
    "Url": "https://media3.spiralknights.com/wiki-images/9/96/Divine_Maedate-Equipped.png"
  },
  {
    "Name": "Volcanic Maedate",
    "Chance": 0.029500157568,
    "Url": "https://media3.spiralknights.com/wiki-images/f/f2/Volcanic_Maedate-Equipped.png"
  },
  {
    "Name": "**Prismatic Maedate**",
    "Chance": 0.005719418304,
    "Url": "https://media3.spiralknights.com/wiki-images/e/eb/Prismatic_Maedate-Equipped.png"
  },
  {
    "Name": "Cool Scarf",
    "Chance": 0.1369108418325943,
    "Url": "https://media3.spiralknights.com/wiki-images/2/27/Cool_Scarf-Equipped.png"
  },
  {
    "Name": "Regal Scarf",
    "Chance": 0.1369108418325943,
    "Url": "https://media3.spiralknights.com/wiki-images/0/03/Regal_Scarf-Equipped.png"
  },
  {
    "Name": "Military Scarf",
    "Chance": 0.1369108418325943,
    "Url": "https://media3.spiralknights.com/wiki-images/0/00/Military_Scarf-Equipped.png"
  },
  {
    "Name": "Heavy Scarf",
    "Chance": 0.1369108418325943,
    "Url": "https://media3.spiralknights.com/wiki-images/9/90/Heavy_Scarf-Equipped.png"
  },
  {
    "Name": "Fancy Scarf",
    "Chance": 0.1369108418325943,
    "Url": "https://media3.spiralknights.com/wiki-images/3/36/Fancy_Scarf-Equipped.png"
  },
  {
    "Name": "Dusky Scarf",
    "Chance": 0.1369108418325943,
    "Url": "https://media3.spiralknights.com/wiki-images/7/70/Dusky_Scarf-Equipped.png"
  },
  {
    "Name": "Toasty Scarf",
    "Chance": 0.1369108418325943,
    "Url": "https://media3.spiralknights.com/wiki-images/b/b3/Toasty_Scarf-Equipped.png"
  },
  {
    "Name": "Divine Scarf",
    "Chance": 0.009598450434048,
    "Url": "https://media3.spiralknights.com/wiki-images/1/14/Divine_Scarf-Equipped.png"
  },
  {
    "Name": "Volcanic Scarf",
    "Chance": 0.009598450434048,
    "Url": "https://media3.spiralknights.com/wiki-images/3/34/Volcanic_Scarf-Equipped.png"
  },
  {
    "Name": "**Prismatic Scarf**",
    "Chance": 0.001860924063744,
    "Url": "https://media3.spiralknights.com/wiki-images/a/a8/Prismatic_Scarf-Equipped.png"
  },
  {
    "Name": "Cool Mustache",
    "Chance": 0.1369108418325943,
    "Url": "https://media3.spiralknights.com/wiki-images/c/ca/Cool_Mustache-Equipped.png"
  },
  {
    "Name": "Regal Mustache",
    "Chance": 0.1369108418325943,
    "Url": "https://media3.spiralknights.com/wiki-images/0/0c/Regal_Mustache-Equipped.png"
  },
  {
    "Name": "Military Mustache",
    "Chance": 0.1369108418325943,
    "Url": "https://media3.spiralknights.com/wiki-images/e/e2/Military_Mustache-Equipped.png"
  },
  {
    "Name": "Heavy Mustache",
    "Chance": 0.1369108418325943,
    "Url": "https://media3.spiralknights.com/wiki-images/3/34/Heavy_Mustache-Equipped.png"
  },
  {
    "Name": "Fancy Mustache",
    "Chance": 0.1369108418325943,
    "Url": "https://media3.spiralknights.com/wiki-images/d/d4/Fancy_Mustache-Equipped.png"
  },
  {
    "Name": "Dusky Mustache",
    "Chance": 0.1369108418325943,
    "Url": "https://media3.spiralknights.com/wiki-images/a/af/Dusky_Mustache-Equipped.png"
  },
  {
    "Name": "Toasty Mustache",
    "Chance": 0.1369108418325943,
    "Url": "https://media3.spiralknights.com/wiki-images/0/07/Toasty_Mustache-Equipped.png"
  },
  {
    "Name": "Divine Mustache",
    "Chance": 0.009598450434048,
    "Url": "https://media3.spiralknights.com/wiki-images/3/3a/Divine_Mustache-Equipped.png"
  },
  {
    "Name": "Volcanic Mustache",
    "Chance": 0.009598450434048,
    "Url": "https://media3.spiralknights.com/wiki-images/f/fb/Volcanic_Mustache-Equipped.png"
  },
  {
    "Name": "**Prismatic Mustache**",
    "Chance": 0.001860924063744,
    "Url": "https://media3.spiralknights.com/wiki-images/d/df/Prismatic_Mustache-Equipped.png"
  },
  {
    "Name": "Cool Mohawk",
    "Chance": 0.1369108418325943,
    "Url": "https://media3.spiralknights.com/wiki-images/6/68/Cool_Mohawk-Equipped.png"
  },
  {
    "Name": "Regal Mohawk",
    "Chance": 0.1369108418325943,
    "Url": "https://media3.spiralknights.com/wiki-images/e/eb/Regal_Mohawk-Equipped.png"
  },
  {
    "Name": "Military Mohawk",
    "Chance": 0.1369108418325943,
    "Url": "https://media3.spiralknights.com/wiki-images/7/77/Military_Mohawk-Equipped.png"
  },
  {
    "Name": "Heavy Mohawk",
    "Chance": 0.1369108418325943,
    "Url": "https://media3.spiralknights.com/wiki-images/e/e1/Heavy_Mohawk-Equipped.png"
  },
  {
    "Name": "Fancy Mohawk",
    "Chance": 0.1369108418325943,
    "Url": "https://media3.spiralknights.com/wiki-images/8/87/Fancy_Mohawk-Equipped.png"
  },
  {
    "Name": "Dusky Mohawk",
    "Chance": 0.1369108418325943,
    "Url": "https://media3.spiralknights.com/wiki-images/a/aa/Dusky_Mohawk-Equipped.png"
  },
  {
    "Name": "Toasty Mohawk",
    "Chance": 0.1369108418325943,
    "Url": "https://media3.spiralknights.com/wiki-images/3/39/Toasty_Mohawk-Equipped.png"
  },
  {
    "Name": "Divine Mohawk",
    "Chance": 0.009598450434048,
    "Url": "https://media3.spiralknights.com/wiki-images/9/97/Divine_Mohawk-Equipped.png"
  },
  {
    "Name": "Volcanic Mohawk",
    "Chance": 0.009598450434048,
    "Url": "https://media3.spiralknights.com/wiki-images/c/ce/Volcanic_Mohawk-Equipped.png"
  },
  {
    "Name": "**Prismatic Mohawk**",
    "Chance": 0.001860924063744,
    "Url": "https://media3.spiralknights.com/wiki-images/a/aa/Prismatic_Mohawk-Equipped.png"
  },
  {
    "Name": "Prismatic Glow-Eyes",
    "Chance": 0.07348764672,
    "Url": "https://media3.spiralknights.com/wiki-images/e/ec/Prismatic_Glow-Eyes-Equipped.png"
  },
  {
    "Name": "Cool Dapper Combo",
    "Chance": 0.0091323011810743,
    "Url": "https://media3.spiralknights.com/wiki-images/2/24/Cool_Dapper_Combo-Equipped.png"
  },
  {
    "Name": "Regal Dapper Combo",
    "Chance": 0.0091323011810743,
    "Url": "https://media3.spiralknights.com/wiki-images/b/b5/Regal_Dapper_Combo-Equipped.png"
  },
  {
    "Name": "Military Dapper Combo",
    "Chance": 0.0091323011810743,
    "Url": "https://media3.spiralknights.com/wiki-images/f/fe/Military_Dapper_Combo-Equipped.png"
  },
  {
    "Name": "Heavy Dapper Combo",
    "Chance": 0.0091323011810743,
    "Url": "https://media3.spiralknights.com/wiki-images/0/0a/Heavy_Dapper_Combo-Equipped.png"
  },
  {
    "Name": "Fancy Dapper Combo",
    "Chance": 0.0091323011810743,
    "Url": "https://media3.spiralknights.com/wiki-images/a/ac/Fancy_Dapper_Combo-Equipped.png"
  },
  {
    "Name": "Dusky Dapper Combo",
    "Chance": 0.0091323011810743,
    "Url": "https://media3.spiralknights.com/wiki-images/4/4d/Dusky_Dapper_Combo-Equipped.png"
  },
  {
    "Name": "Toasty Dapper Combo",
    "Chance": 0.0091323011810743,
    "Url": "https://media3.spiralknights.com/wiki-images/b/be/Toasty_Dapper_Combo-Equipped.png"
  },
  {
    "Name": "Divine Dapper Combo",
    "Chance": 0.000640241043456,
    "Url": "https://media3.spiralknights.com/wiki-images/b/b3/Divine_Dapper_Combo-Equipped.png"
  },
  {
    "Name": "Volcanic Dapper Combo",
    "Chance": 0.000640241043456,
    "Url": "https://media3.spiralknights.com/wiki-images/f/fb/Volcanic_Dapper_Combo-Equipped.png"
  },
  {
    "Name": "**Prismatic Dapper Combo**",
    "Chance": 0.000124128365568,
    "Url": "https://media3.spiralknights.com/wiki-images/3/3b/Prismatic_Dapper_Combo-Equipped.png"
  },
  {
    "Name": "Cool Toupee",
    "Chance": 0.0091323011810743,
    "Url": "https://media3.spiralknights.com/wiki-images/e/e2/Cool_Toupee-Equipped.png"
  },
  {
    "Name": "Regal Toupee",
    "Chance": 0.0091323011810743,
    "Url": "https://media3.spiralknights.com/wiki-images/c/cf/Regal_Toupee-Equipped.png"
  },
  {
    "Name": "Military Toupee",
    "Chance": 0.0091323011810743,
    "Url": "https://media3.spiralknights.com/wiki-images/c/c2/Military_Toupee-Equipped.png"
  },
  {
    "Name": "Heavy Toupee",
    "Chance": 0.0091323011810743,
    "Url": "https://media3.spiralknights.com/wiki-images/9/92/Heavy_Toupee-Equipped.png"
  },
  {
    "Name": "Fancy Toupee",
    "Chance": 0.0091323011810743,
    "Url": "https://media3.spiralknights.com/wiki-images/f/f2/Fancy_Toupee-Equipped.png"
  },
  {
    "Name": "Dusky Toupee",
    "Chance": 0.0091323011810743,
    "Url": "https://media3.spiralknights.com/wiki-images/f/f0/Dusky_Toupee-Equipped.png"
  },
  {
    "Name": "Toasty Toupee",
    "Chance": 0.0091323011810743,
    "Url": "https://media3.spiralknights.com/wiki-images/f/fb/Toasty_Toupee-Equipped.png"
  },
  {
    "Name": "Divine Toupee",
    "Chance": 0.000640241043456,
    "Url": "https://media3.spiralknights.com/wiki-images/3/3a/Divine_Toupee-Equipped.png"
  },
  {
    "Name": "Volcanic Toupee",
    "Chance": 0.000640241043456,
    "Url": "https://media3.spiralknights.com/wiki-images/4/49/Volcanic_Toupee-Equipped.png"
  },
  {
    "Name": "**Prismatic Toupee**",
    "Chance": 0.000124128365568,
    "Url": "https://media3.spiralknights.com/wiki-images/b/b9/Prismatic_Toupee-Equipped.png"
  },
  {
    "Name": "**Divine Halo**",
    "Chance": 0.00647743744,
    "Url": "https://media3.spiralknights.com/wiki-images/c/ca/Divine_Halo-Equipped.png"
  },
  {
    "Name": "**Volcanic Halo**",
    "Chance": 0.00647743744,
    "Url": "https://media3.spiralknights.com/wiki-images/e/e8/Volcanic_Halo-Equipped.png"
  },
  {
    "Name": "**Prismatic Halo**",
    "Chance": 0.00647743744,
    "Url": "https://media3.spiralknights.com/wiki-images/f/fd/Prismatic_Halo-Equipped.png"
  },
  {
    "Name": "Cool Vitakit",
    "Chance": 0.7014923532571429,
    "Url": "https://media3.spiralknights.com/wiki-images/a/ac/Cool_Vitakit-Equipped.png"
  },
  {
    "Name": "Regal Vitakit",
    "Chance": 0.7014923532571429,
    "Url": "https://media3.spiralknights.com/wiki-images/3/31/Regal_Vitakit-Equipped.png"
  },
  {
    "Name": "Military Vitakit",
    "Chance": 0.7014923532571429,
    "Url": "https://media3.spiralknights.com/wiki-images/4/44/Military_Vitakit-Equipped.png"
  },
  {
    "Name": "Heavy Vitakit",
    "Chance": 0.7014923532571429,
    "Url": "https://media3.spiralknights.com/wiki-images/0/02/Heavy_Vitakit-Equipped.png"
  },
  {
    "Name": "Fancy Vitakit",
    "Chance": 0.7014923532571429,
    "Url": "https://media3.spiralknights.com/wiki-images/c/cb/Fancy_Vitakit-Equipped.png"
  },
  {
    "Name": "Dusky Vitakit",
    "Chance": 0.7014923532571429,
    "Url": "https://media3.spiralknights.com/wiki-images/8/8e/Dusky_Vitakit-Equipped.png"
  },
  {
    "Name": "Toasty Vitakit",
    "Chance": 0.7014923532571429,
    "Url": "https://media3.spiralknights.com/wiki-images/a/af/Toasty_Vitakit-Equipped.png"
  },
  {
    "Name": "Divine Vitakit",
    "Chance": 0.04917973984,
    "Url": "https://media3.spiralknights.com/wiki-images/7/70/Divine_Vitakit-Equipped.png"
  },
  {
    "Name": "Volcanic Vitakit",
    "Chance": 0.04917973984,
    "Url": "https://media3.spiralknights.com/wiki-images/1/1f/Volcanic_Vitakit-Equipped.png"
  },
  {
    "Name": "**Prismatic Vitakit**",
    "Chance": 0.00953484752,
    "Url": "https://media3.spiralknights.com/wiki-images/6/63/Prismatic_Vitakit-Equipped.png"
  },
  {
    "Name": "Cool Canteen",
    "Chance": 0.7014923532571429,
    "Url": "https://media3.spiralknights.com/wiki-images/9/98/Cool_Canteen-Equipped.png"
  },
  {
    "Name": "Regal Canteen",
    "Chance": 0.7014923532571429,
    "Url": "https://media3.spiralknights.com/wiki-images/3/34/Regal_Canteen-Equipped.png"
  },
  {
    "Name": "Military Canteen",
    "Chance": 0.7014923532571429,
    "Url": "https://media3.spiralknights.com/wiki-images/e/ee/Military_Canteen-Equipped.png"
  },
  {
    "Name": "Heavy Canteen",
    "Chance": 0.7014923532571429,
    "Url": "https://media3.spiralknights.com/wiki-images/a/a7/Heavy_Canteen-Equipped.png"
  },
  {
    "Name": "Fancy Canteen",
    "Chance": 0.7014923532571429,
    "Url": "https://media3.spiralknights.com/wiki-images/e/ee/Fancy_Canteen-Equipped.png"
  },
  {
    "Name": "Dusky Canteen",
    "Chance": 0.7014923532571429,
    "Url": "https://media3.spiralknights.com/wiki-images/5/5d/Dusky_Canteen-Equipped.png"
  },
  {
    "Name": "Toasty Canteen",
    "Chance": 0.7014923532571429,
    "Url": "https://media3.spiralknights.com/wiki-images/8/89/Toasty_Canteen-Equipped.png"
  },
  {
    "Name": "Divine Canteen",
    "Chance": 0.04917973984,
    "Url": "https://media3.spiralknights.com/wiki-images/2/2f/Divine_Canteen-Equipped.png"
  },
  {
    "Name": "Volcanic Canteen",
    "Chance": 0.04917973984,
    "Url": "https://media3.spiralknights.com/wiki-images/5/5d/Volcanic_Canteen-Equipped.png"
  },
  {
    "Name": "**Prismatic Canteen**",
    "Chance": 0.00953484752,
    "Url": "https://media3.spiralknights.com/wiki-images/4/4e/Prismatic_Canteen-Equipped.png"
  },
  {
    "Name": "Cool Barrel Belly",
    "Chance": 0.7014923532571429,
    "Url": "https://media3.spiralknights.com/wiki-images/a/a5/Cool_Barrel_Belly-Equipped.png"
  },
  {
    "Name": "Regal Barrel Belly",
    "Chance": 0.7014923532571429,
    "Url": "https://media3.spiralknights.com/wiki-images/c/ce/Regal_Barrel_Belly-Equipped.png"
  },
  {
    "Name": "Military Barrel Belly",
    "Chance": 0.7014923532571429,
    "Url": "https://media3.spiralknights.com/wiki-images/2/28/Military_Barrel_Belly-Equipped.png"
  },
  {
    "Name": "Heavy Barrel Belly",
    "Chance": 0.7014923532571429,
    "Url": "https://media3.spiralknights.com/wiki-images/8/80/Heavy_Barrel_Belly-Equipped.png"
  },
  {
    "Name": "Fancy Barrel Belly",
    "Chance": 0.7014923532571429,
    "Url": "https://media3.spiralknights.com/wiki-images/2/2c/Fancy_Barrel_Belly-Equipped.png"
  },
  {
    "Name": "Dusky Barrel Belly",
    "Chance": 0.7014923532571429,
    "Url": "https://media3.spiralknights.com/wiki-images/d/dd/Dusky_Barrel_Belly-Equipped.png"
  },
  {
    "Name": "Toasty Barrel Belly",
    "Chance": 0.7014923532571429,
    "Url": "https://media3.spiralknights.com/wiki-images/3/3d/Toasty_Barrel_Belly-Equipped.png"
  },
  {
    "Name": "Divine Barrel Belly",
    "Chance": 0.04917973984,
    "Url": "https://media3.spiralknights.com/wiki-images/1/17/Divine_Barrel_Belly-Equipped.png"
  },
  {
    "Name": "Volcanic Barrel Belly",
    "Chance": 0.04917973984,
    "Url": "https://media3.spiralknights.com/wiki-images/8/8d/Volcanic_Barrel_Belly-Equipped.png"
  },
  {
    "Name": "**Prismatic Barrel Belly**",
    "Chance": 0.00953484752,
    "Url": "https://media3.spiralknights.com/wiki-images/d/d5/Prismatic_Barrel_Belly-Equipped.png"
  },
  {
    "Name": "Cool Side Blade",
    "Chance": 0.2629911095142857,
    "Url": "https://media3.spiralknights.com/wiki-images/0/08/Cool_Side_Blade-Equipped.png"
  },
  {
    "Name": "Regal Side Blade",
    "Chance": 0.2629911095142857,
    "Url": "https://media3.spiralknights.com/wiki-images/0/0f/Regal_Side_Blade-Equipped.png"
  },
  {
    "Name": "Military Side Blade",
    "Chance": 0.2629911095142857,
    "Url": "https://media3.spiralknights.com/wiki-images/6/68/Military_Side_Blade-Equipped.png"
  },
  {
    "Name": "Heavy Side Blade",
    "Chance": 0.2629911095142857,
    "Url": "https://media3.spiralknights.com/wiki-images/3/38/Heavy_Side_Blade-Equipped.png"
  },
  {
    "Name": "Fancy Side Blade",
    "Chance": 0.2629911095142857,
    "Url": "https://media3.spiralknights.com/wiki-images/2/2d/Fancy_Side_Blade-Equipped.png"
  },
  {
    "Name": "Dusky Side Blade",
    "Chance": 0.2629911095142857,
    "Url": "https://media3.spiralknights.com/wiki-images/7/76/Dusky_Side_Blade-Equipped.png"
  },
  {
    "Name": "Toasty Side Blade",
    "Chance": 0.2629911095142857,
    "Url": "https://media3.spiralknights.com/wiki-images/d/d8/Toasty_Side_Blade-Equipped.png"
  },
  {
    "Name": "Divine Side Blade",
    "Chance": 0.01843759848,
    "Url": "https://media3.spiralknights.com/wiki-images/b/bf/Divine_Side_Blade-Equipped.png"
  },
  {
    "Name": "Volcanic Side Blade",
    "Chance": 0.01843759848,
    "Url": "https://media3.spiralknights.com/wiki-images/3/32/Volcanic_Side_Blade-Equipped.png"
  },
  {
    "Name": "**Prismatic Side Blade**",
    "Chance": 0.00357463644,
    "Url": "https://media3.spiralknights.com/wiki-images/8/8c/Prismatic_Side_Blade-Equipped.png"
  },
  {
    "Name": "Cool Bomb Bandolier",
    "Chance": 0.2629911095142857,
    "Url": "https://media3.spiralknights.com/wiki-images/d/df/Cool_Bomb_Bandolier-Equipped.png"
  },
  {
    "Name": "Regal Bomb Bandolier",
    "Chance": 0.2629911095142857,
    "Url": "https://media3.spiralknights.com/wiki-images/7/7a/Regal_Bomb_Bandolier-Equipped.png"
  },
  {
    "Name": "Military Bomb Bandolier",
    "Chance": 0.2629911095142857,
    "Url": "https://media3.spiralknights.com/wiki-images/5/55/Military_Bomb_Bandolier-Equipped.png"
  },
  {
    "Name": "Heavy Bomb Bandolier",
    "Chance": 0.2629911095142857,
    "Url": "https://media3.spiralknights.com/wiki-images/e/e3/Heavy_Bomb_Bandolier-Equipped.png"
  },
  {
    "Name": "Fancy Bomb Bandolier",
    "Chance": 0.2629911095142857,
    "Url": "https://media3.spiralknights.com/wiki-images/5/5e/Fancy_Bomb_Bandolier-Equipped.png"
  },
  {
    "Name": "Dusky Bomb Bandolier",
    "Chance": 0.2629911095142857,
    "Url": "https://media3.spiralknights.com/wiki-images/c/ca/Dusky_Bomb_Bandolier-Equipped.png"
  },
  {
    "Name": "Toasty Bomb Bandolier",
    "Chance": 0.2629911095142857,
    "Url": "https://media3.spiralknights.com/wiki-images/8/82/Toasty_Bomb_Bandolier-Equipped.png"
  },
  {
    "Name": "Divine Bomb Bandolier",
    "Chance": 0.01843759848,
    "Url": "https://media3.spiralknights.com/wiki-images/f/f2/Divine_Bomb_Bandolier-Equipped.png"
  },
  {
    "Name": "Volcanic Bomb Bandolier",
    "Chance": 0.01843759848,
    "Url": "https://media3.spiralknights.com/wiki-images/e/ea/Volcanic_Bomb_Bandolier-Equipped.png"
  },
  {
    "Name": "**Prismatic Bomb Bandolier**",
    "Chance": 0.00357463644,
    "Url": "https://media3.spiralknights.com/wiki-images/9/9d/Prismatic_Bomb_Bandolier-Equipped.png"
  },
  {
    "Name": "Cool Wolver Tail",
    "Chance": 0.0526256310857143,
    "Url": "https://media3.spiralknights.com/wiki-images/9/9c/Cool_Wolver_Tail-Equipped.png"
  },
  {
    "Name": "Regal Wolver Tail",
    "Chance": 0.0526256310857143,
    "Url": "https://media3.spiralknights.com/wiki-images/7/7e/Regal_Wolver_Tail-Equipped.png"
  },
  {
    "Name": "Military Wolver Tail",
    "Chance": 0.0526256310857143,
    "Url": "https://media3.spiralknights.com/wiki-images/a/ab/Military_Wolver_Tail-Equipped.png"
  },
  {
    "Name": "Heavy Wolver Tail",
    "Chance": 0.0526256310857143,
    "Url": "https://media3.spiralknights.com/wiki-images/2/20/Heavy_Wolver_Tail-Equipped.png"
  },
  {
    "Name": "Fancy Wolver Tail",
    "Chance": 0.0526256310857143,
    "Url": "https://media3.spiralknights.com/wiki-images/7/79/Fancy_Wolver_Tail-Equipped.png"
  },
  {
    "Name": "Dusky Wolver Tail",
    "Chance": 0.0526256310857143,
    "Url": "https://media3.spiralknights.com/wiki-images/2/29/Dusky_Wolver_Tail-Equipped.png"
  },
  {
    "Name": "Toasty Wolver Tail",
    "Chance": 0.0526256310857143,
    "Url": "https://media3.spiralknights.com/wiki-images/9/97/Toasty_Wolver_Tail-Equipped.png"
  },
  {
    "Name": "Divine Wolver Tail",
    "Chance": 0.00368944128,
    "Url": "https://media3.spiralknights.com/wiki-images/7/7a/Divine_Wolver_Tail-Equipped.png"
  },
  {
    "Name": "Volcanic Wolver Tail",
    "Chance": 0.00368944128,
    "Url": "https://media3.spiralknights.com/wiki-images/c/c3/Volcanic_Wolver_Tail-Equipped.png"
  },
  {
    "Name": "**Prismatic Wolver Tail**",
    "Chance": 0.00071529984,
    "Url": "https://media3.spiralknights.com/wiki-images/1/11/Prismatic_Wolver_Tail-Equipped.png"
  },
  {
    "Name": "Cool Parrying Blade",
    "Chance": 0.0526256310857143,
    "Url": "https://media3.spiralknights.com/wiki-images/c/c6/Cool_Parrying_Blade-Equipped.png"
  },
  {
    "Name": "Regal Parrying Blade",
    "Chance": 0.0526256310857143,
    "Url": "https://media3.spiralknights.com/wiki-images/4/48/Regal_Parrying_Blade-Equipped.png"
  },
  {
    "Name": "Military Parrying Blade",
    "Chance": 0.0526256310857143,
    "Url": "https://media3.spiralknights.com/wiki-images/c/ce/Military_Parrying_Blade-Equipped.png"
  },
  {
    "Name": "Heavy Parrying Blade",
    "Chance": 0.0526256310857143,
    "Url": "https://media3.spiralknights.com/wiki-images/c/cd/Heavy_Parrying_Blade-Equipped.png"
  },
  {
    "Name": "Fancy Parrying Blade",
    "Chance": 0.0526256310857143,
    "Url": "https://media3.spiralknights.com/wiki-images/e/ef/Fancy_Parrying_Blade-Equipped.png"
  },
  {
    "Name": "Dusky Parrying Blade",
    "Chance": 0.0526256310857143,
    "Url": "https://media3.spiralknights.com/wiki-images/1/1a/Dusky_Parrying_Blade-Equipped.png"
  },
  {
    "Name": "Toasty Parrying Blade",
    "Chance": 0.0526256310857143,
    "Url": "https://media3.spiralknights.com/wiki-images/1/1c/Toasty_Parrying_Blade-Equipped.png"
  },
  {
    "Name": "Divine Parrying Blade",
    "Chance": 0.00368944128,
    "Url": "https://media3.spiralknights.com/wiki-images/3/3b/Divine_Parrying_Blade-Equipped.png"
  },
  {
    "Name": "Volcanic Parrying Blade",
    "Chance": 0.00368944128,
    "Url": "https://media3.spiralknights.com/wiki-images/0/0b/Volcanic_Parrying_Blade-Equipped.png"
  },
  {
    "Name": "**Prismatic Parrying Blade**",
    "Chance": 0.00071529984,
    "Url": "https://media3.spiralknights.com/wiki-images/6/6f/Prismatic_Parrying_Blade-Equipped.png"
  },
  {
    "Name": "**Twinkle Aura**",
    "Chance": 0.00517474728,
    "Url": "https://media3.spiralknights.com/wiki-images/7/7f/Twinkle_Aura-Equipped.png"
  },
  {
    "Name": "**Ghostly Aura**",
    "Chance": 0.00517474728,
    "Url": "https://media3.spiralknights.com/wiki-images/2/26/Ghostly_Aura-Equipped.png"
  },
  {
    "Name": "**Unclean Aura**",
    "Chance": 0.00517474728,
    "Url": "https://media3.spiralknights.com/wiki-images/f/f9/Unclean_Aura-Equipped.png"
  },
  {
    "Name": "**Twilight Aura**",
    "Chance": 0.00258737364,
    "Url": "https://media3.spiralknights.com/wiki-images/b/b3/Twilight_Aura-Equipped.png"
  },
  {
    "Name": "**Flame Aura**",
    "Chance": 0.00051598452,
    "Url": "https://media3.spiralknights.com/wiki-images/f/f5/Flame_Aura-Equipped.png"
  },
  {
    "Name": "Cool Wings",
    "Chance": 0.0026038723714286,
    "Url": "https://media3.spiralknights.com/wiki-images/b/b2/Cool_Wings-Equipped.png"
  },
  {
    "Name": "Regal Wings",
    "Chance": 0.0026038723714286,
    "Url": "https://media3.spiralknights.com/wiki-images/9/98/Regal_Wings-Equipped.png"
  },
  {
    "Name": "Military Wings",
    "Chance": 0.0026038723714286,
    "Url": "https://media3.spiralknights.com/wiki-images/4/4c/Military_Wings-Equipped.png"
  },
  {
    "Name": "Heavy Wings",
    "Chance": 0.0026038723714286,
    "Url": "https://media3.spiralknights.com/wiki-images/c/c4/Heavy_Wings-Equipped.png"
  },
  {
    "Name": "Fancy Wings",
    "Chance": 0.0026038723714286,
    "Url": "https://media3.spiralknights.com/wiki-images/0/07/Fancy_Wings-Equipped.png"
  },
  {
    "Name": "Dusky Wings",
    "Chance": 0.0026038723714286,
    "Url": "https://media3.spiralknights.com/wiki-images/5/50/Dusky_Wings-Equipped.png"
  },
  {
    "Name": "Toasty Wings",
    "Chance": 0.0026038723714286,
    "Url": "https://media3.spiralknights.com/wiki-images/f/fc/Toasty_Wings-Equipped.png"
  },
  {
    "Name": "Divine Wings",
    "Chance": 0.00018255048,
    "Url": "https://media3.spiralknights.com/wiki-images/b/ba/Divine_Wings-Equipped.png"
  },
  {
    "Name": "Volcanic Wings",
    "Chance": 0.00018255048,
    "Url": "https://media3.spiralknights.com/wiki-images/9/9f/Volcanic_Wings-Equipped.png"
  },
  {
    "Name": "**Prismatic Wings**",
    "Chance": 0.00003539244,
    "Url": "https://media3.spiralknights.com/wiki-images/e/ee/Prismatic_Wings-Equipped.png"
  },
  {
    "Name": "Shadow Key",
    "Chance": 1.96,
    "Url": "https://media3.spiralknights.com/wiki-images/3/34/Key-Shadow_Key_icon.png"
  }
]
